[{"distnum":1,"year":2026,"mail_ballots":17553,"in_person":50221,"outstanding_applications":22814,"total":67774},{"distnum":2,"year":2026,"mail_ballots":18845,"in_person":28681,"outstanding_applications":23846,"total":47526},{"distnum":3,"year":2026,"mail_ballots":13482,"in_person":16159,"outstanding_applications":18749,"total":29641},{"distnum":4,"year":2026,"mail_ballots":12930,"in_person":29976,"outstanding_applications":20344,"total":42906},{"distnum":5,"year":2026,"mail_ballots":13645,"in_person":44074,"outstanding_applications":17911,"total":57719},{"distnum":6,"year":2026,"mail_ballots":12212,"in_person":42227,"outstanding_applications":12349,"total":54439},{"distnum":7,"year":2026,"mail_ballots":16415,"in_person":24577,"outstanding_applications":21475,"total":40992},{"distnum":8,"year":2026,"mail_ballots":18958,"in_person":16461,"outstanding_applications":27326,"total":35419},{"distnum":9,"year":2026,"mail_ballots":10785,"in_person":36732,"outstanding_applications":10899,"total":47517},{"distnum":10,"year":2026,"mail_ballots":17220,"in_person":20646,"outstanding_applications":24612,"total":37866},{"distnum":11,"year":2026,"mail_ballots":21293,"in_person":16430,"outstanding_applications":30099,"total":37723},{"distnum":1,"year":2025,"mail_ballots":36998,"in_person":151582,"outstanding_applications":8091,"total":188580},{"distnum":2,"year":2025,"mail_ballots":36462,"in_person":98756,"outstanding_applications":10569,"total":135218},{"distnum":3,"year":2025,"mail_ballots":26689,"in_person":63291,"outstanding_applications":8384,"total":89980},{"distnum":4,"year":2025,"mail_ballots":28462,"in_person":106261,"outstanding_applications":7149,"total":134723},{"distnum":5,"year":2025,"mail_ballots":27675,"in_person":114595,"outstanding_applications":7700,"total":142270},{"distnum":6,"year":2025,"mail_ballots":21627,"in_person":105172,"outstanding_applications":5786,"total":126799},{"distnum":7,"year":2025,"mail_ballots":32373,"in_person":96507,"outstanding_applications":9257,"total":128880},{"distnum":8,"year":2025,"mail_ballots":40934,"in_person":97849,"outstanding_applications":13231,"total":138783},{"distnum":9,"year":2025,"mail_ballots":18951,"in_person":93193,"outstanding_applications":5019,"total":112144},{"distnum":10,"year":2025,"mail_ballots":36328,"in_person":108184,"outstanding_applications":10815,"total":144512},{"distnum":11,"year":2025,"mail_ballots":45205,"in_person":98319,"outstanding_applications":13154,"total":143524}]